kroma/__init__.py
kroma/ansi_tools.py
kroma/color_utilities.py
kroma/enums.py
kroma/exceptions.py
kroma/gradients.py
kroma/gv.py
kroma/palettes.py
kroma/styles.py
kroma/utils.py
kroma-2.2.2.dist-info/METADATA
kroma-2.2.2.dist-info/WHEEL
kroma-2.2.2.dist-info/licenses/LICENSE
kroma-2.2.2.dist-info/RECORD
