Metadata-Version: 2.4
Name: kroma
Version: 2.2.2
Summary: A lightweight and powerful colors library for terminal output in Python.
Project-URL: Documentation, https://www.powerpcfan.xyz/docs/kroma/v2/
Project-URL: Repository, https://github.com/PowerPCFan/kroma
Project-URL: Issues, https://github.com/PowerPCFan/kroma/issues
Author-email: PowerPCFan <charlie@powerpcfan.xyz>
Maintainer-email: PowerPCFan <charlie@powerpcfan.xyz>
License-Expression: AGPL-3.0-only
License-File: LICENSE
Classifier: Development Status :: 5 - Production/Stable
Classifier: Intended Audience :: Developers
Classifier: Programming Language :: Python
Classifier: Programming Language :: Python :: 3
Classifier: Programming Language :: Python :: 3.10
Classifier: Programming Language :: Python :: 3.11
Classifier: Programming Language :: Python :: 3.12
Classifier: Programming Language :: Python :: 3.13
Requires-Python: >=3.10
